<?xml version="1.0" encoding="UTF-8"?>
<?Business Samples for ISO submission?>
<?valid true?>
<Document xmlns:xsi="http://www.w3.org/2001/XMLSchema-instance" xmlns="urn:iso:std:iso:20022:tech:xsd:sese.032.001.01">
	<SctiesSttlmTxGnrtnNtfctn>
		<Id>
			<Id>FDGTRU65498</Id>
		</Id>
		<TxIdDtls>
			<AcctOwnrTxId>FRTJ123DEL2</AcctOwnrTxId>
			<SctiesMvmntTp>DELI</SctiesMvmntTp>
			<Pmt>APMT</Pmt>
			<CorpActnEvtId>4578965478</CorpActnEvtId>
		</TxIdDtls>
		<TradDtls>
			<TradDt>
				<Dt>
					<Dt>2010-01-05</Dt>
				</Dt>
			</TradDt>
			<SttlmDt>
				<Dt>
					<Dt>2010-01-08</Dt>
				</Dt>
			</SttlmDt>
			<DealPric>
				<Tp>
					<ValTp>PARV</ValTp>
				</Tp>
				<Val>
					<Rate>101.002</Rate>
				</Val>
			</DealPric>
		</TradDtls>
		<FinInstrmId>
			<Id>
				<ISIN>BE0987654321</ISIN>
			</Id>
			<Desc>Belgium Company ZYX</Desc>
		</FinInstrmId>
		<QtyAndAcctDtls>
			<SttlmQty>
				<Qty>
					<FaceAmt>5500000</FaceAmt>
				</Qty>
			</SttlmQty>
			<SfkpgAcct>
				<Id>222S</Id>
			</SfkpgAcct>
		</QtyAndAcctDtls>
		<SttlmParams>
			<SctiesTxTp>
				<Cd>TRAD</Cd>
			</SctiesTxTp>
		</SttlmParams>
		<RcvgSttlmPties>
			<Dpstry>
				<Id>
					<BICOrBEI>NBBEBEBB</BICOrBEI>
				</Id>
			</Dpstry>
			<Pty1>
				<Id>
					<BICOrBEI>CITIBEBB</BICOrBEI>
				</Id>
			</Pty1>
			<Pty2>
				<Id>
					<BICOrBEI>CFPIDEFF</BICOrBEI>
				</Id>
				<SfkpgAcct>
					<Id>321654</Id>
				</SfkpgAcct>
			</Pty2>
		</RcvgSttlmPties>
		<SttlmAmt>
			<AcrdIntrstInd>true</AcrdIntrstInd>
			<Amt Ccy="EUR">50850000</Amt>
			<CdtDbtInd>CRDT</CdtDbtInd>
		</SttlmAmt>
		<GnrtdRsn>
			<Cd>
				<Cd>TRAN</Cd>
			</Cd>
		</GnrtdRsn>
	</SctiesSttlmTxGnrtnNtfctn>
</Document>
