<?xml version="1.0" encoding="UTF-8"?>
<?Business Samples for ISO submission?>
<?valid true?>
<?description Plain vanilla fixed income sample for documentation.?>
<Document xmlns:xsi="http://www.w3.org/2001/XMLSchema-instance" xmlns="urn:iso:std:iso:20022:tech:xsd:sese.023.001.03">
	<SctiesSttlmTxInstr>
		<TxId>FRTJ123REC2</TxId>
		<SttlmTpAndAddtlParams>
			<SctiesMvmntTp>RECE</SctiesMvmntTp>
			<Pmt>APMT</Pmt>
		</SttlmTpAndAddtlParams>
		<TradDtls>
			<TradDt>
				<Dt>
					<Dt>2010-01-12</Dt>
				</Dt>
			</TradDt>
			<SttlmDt>
				<Dt>
					<Dt>2010-01-15</Dt>
				</Dt>
			</SttlmDt>
			<DealPric>
				<Tp>
					<ValTp>PARV</ValTp>
				</Tp>
				<Val>
					<Rate>101.001283</Rate>
				</Val>
			</DealPric>
		</TradDtls>
		<FinInstrmId>
			<ISIN>GB0987654321</ISIN>
		</FinInstrmId>
		<QtyAndAcctDtls>
			<SttlmQty>
				<Qty>
					<FaceAmt>4000000</FaceAmt>
				</Qty>
			</SttlmQty>
			<SfkpgAcct>
				<Id>222S</Id>
			</SfkpgAcct>
		</QtyAndAcctDtls>
		<SttlmParams>
			<SctiesTxTp>
				<Cd>TRAD</Cd>
			</SctiesTxTp>
		</SttlmParams>
		<DlvrgSttlmPties>
			<Dpstry>
				<Id>
					<AnyBIC>CRSTGB22</AnyBIC>
				</Id>
			</Dpstry>
			<Pty1>
				<Id>
					<PrtryId>
						<Id>456</Id>
						<Issr>CRST</Issr>
					</PrtryId>
				</Id>
			</Pty1>
			<Pty2>
				<Id>
					<AnyBIC>CPFIDEFF</AnyBIC>
				</Id>
			</Pty2>
		</DlvrgSttlmPties>
		<RcvgSttlmPties>
			<Pty1>
				<Id>
					<PrtryId>
						<Id>123</Id>
						<Issr>CRST</Issr>
					</PrtryId>
				</Id>
			</Pty1>
			<Pty2>
				<Id>
					<AnyBIC>DRESDEFF</AnyBIC>
				</Id>
			</Pty2>
			<Pty3>
				<Id>
					<AnyBIC>MGTCDE55</AnyBIC>
				</Id>
				<SfkpgAcct>
					<Id>111S</Id>
				</SfkpgAcct>
			</Pty3>
		</RcvgSttlmPties>
		<SttlmAmt>
			<AcrdIntrstInd>true</AcrdIntrstInd>
			<Amt Ccy="GBP">4047151.3</Amt>
			<CdtDbtInd>DBIT</CdtDbtInd>
		</SttlmAmt>
	</SctiesSttlmTxInstr>
</Document>
