<?xml version="1.0" encoding="utf-8"?>
<Document xmlns:xsi="http://www.w3.org/2001/XMLSchema-instance" xmlns="urn:iso:std:iso:20022:tech:xsd:caaa.011.001.02">
	<AccptrBtchTrf>
		<Hdr>
			<DwnldTrf>false</DwnldTrf>
			<FrmtVrsn>02.00</FrmtVrsn>
			<XchgId>096</XchgId>
			<CreDtTm>2013-11-11T09:09:49.34+02:00</CreDtTm>
			<InitgPty>
				<Id>66000001</Id>
				<Tp>OPOI</Tp>
				<Issr>ACQR</Issr>
				<ShrtNm>C=FR, O=EPASOrg, CN=9715239646</ShrtNm>
			</InitgPty>
			<RcptPty>
				<Id>epas-acquirer-1</Id>
				<Tp>ACQR</Tp>
			</RcptPty>
		</Hdr>
		<BtchTrf>
		 <TxTtls>
			<CardPdctPrfl>0001</CardPdctPrfl>
			<Ccy>EUR</Ccy>
			<Tp>DEBT</Tp>
			<TtlNb>2</TtlNb>
			<CmltvAmt>68.14</CmltvAmt>
		 </TxTtls>
		 <DataSet>
			<DataSetId>
				<Nm>Txn004</Nm>
				<Tp>TXCP</Tp>
				<CreDtTm>2013-11-11T09:09:49.34+02:00</CreDtTm>
			</DataSetId>
			<DataSetInitr>
				<Id>66000001</Id>
				<Tp>OPOI</Tp>
				<Issr>ACQR</Issr>
				<ShrtNm>C=FR, O=EPASOrg, CN=9715239646</ShrtNm>
			</DataSetInitr>
			<TxTtls>
				<CardPdctPrfl>0001</CardPdctPrfl>
				<Ccy>EUR</Ccy>
				<Tp>DEBT</Tp>
				<TtlNb>2</TtlNb>
				<CmltvAmt>68.14</CmltvAmt>
			</TxTtls>
			<CmonData>
				<Envt>
					<Acqrr>
						<Id>
							<Id>epas-acquirer-1</Id>
							<Tp>ACQR</Tp>
						</Id>
						<ParamsVrsn>2013-08-07 08:00:00</ParamsVrsn>
					</Acqrr>
					<Mrchnt>
						<Id>
							<Id>EPASMER001</Id>
							<Tp>MERC</Tp>
						</Id>
					</Mrchnt>
					<POI>
						<Id>
							<Id>66000001</Id>
							<Tp>OPOI</Tp>
							<Issr>ACQR</Issr>
						</Id>
						<SysNm>POI01</SysNm>
						<Cpblties>
							<CardRdngCpblties>CICC</CardRdngCpblties>
							<CardRdngCpblties>MGST</CardRdngCpblties>
							<CardRdngCpblties>PHYS</CardRdngCpblties>
							<CrdhldrVrfctnCpblties>MNSG</CrdhldrVrfctnCpblties>
							<CrdhldrVrfctnCpblties>FCPN</CrdhldrVrfctnCpblties>
							<CrdhldrVrfctnCpblties>FEPN</CrdhldrVrfctnCpblties>
							<CrdhldrVrfctnCpblties>NPIN</CrdhldrVrfctnCpblties>
							<OnLineCpblties>SMON</OnLineCpblties>
							<DispCpblties>
								<DispTp>CDSP</DispTp>
								<NbOfLines>4</NbOfLines>
								<LineWidth>40</LineWidth>
							</DispCpblties>
							<DispCpblties>
								<DispTp>MDSP</DispTp>
								<NbOfLines>4</NbOfLines>
								<LineWidth>40</LineWidth>
							</DispCpblties>
							<PrtLineWidth>48</PrtLineWidth>
						</Cpblties>
						<Cmpnt>
							<Tp>TERM</Tp>
							<Id>
								<ItmNb>1</ItmNb>
								<PrvdrId>EPASVendor001</PrvdrId>
								<Id>SmartPOI-8539</Id>
								<SrlNb>7825410759</SrlNb>
							</Id>
						</Cmpnt>
						<Cmpnt>
							<Tp>APLI</Tp>
							<Id>
								<ItmNb>1</ItmNb>
								<PrvdrId>EPASVendor001</PrvdrId>
							</Id>
							<Sts>
								<VrsnNb>1.0</VrsnNb>
							</Sts>
							<StdCmplc>
								<Id>SEPA-FAST</Id>
								<Vrsn>3.0</Vrsn>
								<Issr>CIR</Issr>
							</StdCmplc>
						</Cmpnt>
					</POI>
				</Envt>
				<TxTp>CRDP</TxTp>
				<MrchntCtgyCd>5411</MrchntCtgyCd>
				<RcncltnId>8469</RcncltnId>
			</CmonData>
			<Tx>
			 <Cmpltn>
				<TxSeqCntr>1</TxSeqCntr>
				<Envt>
					<Card>
						<PrtctdCardData>
							<CnttTp>EVLP</CnttTp>
							<EnvlpdData>
								<Vrsn>0</Vrsn>
								<Rcpt>
									<KEK>
										<Vrsn>4</Vrsn>
										<KEKId>
											<KeyId>SpecV1TestKey</KeyId>
											<KeyVrsn>2010060715</KeyVrsn>
											<DerivtnId>OYclpQE=</DerivtnId>
										</KEKId>
										<KeyNcrptnAlgo>
											<Algo>DKP9</Algo>
										</KeyNcrptnAlgo>
										<NcrptdKey>4pAgABg=</NcrptdKey>
									</KEK>
								</Rcpt>
								<NcrptdCntt>
									<CnttTp>DATA</CnttTp>
									<CnttNcrptnAlgo>
										<Algo>E3DC</Algo>
										<Param>
											<InitlstnVctr>onu0bRwwbgk=</InitlstnVctr>
										</Param>
									</CnttNcrptnAlgo>
									<NcrptdData>/swslg9VJdgqgrnmQZNFRaaKVWsB4FlJyIj3UtxClq6jdwRODpJvQIQqhO711twnHCjX9+3bQM0tyvONPgI4qlgRyHnvkr8y</NcrptdData>
								</NcrptdCntt>
							</EnvlpdData>
						</PrtctdCardData>
						<CardPdctPrfl>0001</CardPdctPrfl>
					</Card>
					<Crdhldr>
						<Authntcn>
							<AuthntcnMtd>FPIN</AuthntcnMtd>
							<AuthntcnNtty>ICCD</AuthntcnNtty>
						</Authntcn>
					</Crdhldr>
				</Envt>
				<Cntxt>
					<PmtCntxt>
						<CardPres>true</CardPres>
						<CrdhldrPres>true</CrdhldrPres>
						<OnLineCntxt>true</OnLineCntxt>
						<AttndncCntxt>ATTD</AttndncCntxt>
						<AttndntMsgCpbl>true</AttndntMsgCpbl>
						<CardDataNtryMd>CICC</CardDataNtryMd>
					</PmtCntxt>
					<SaleCntxt>
						<SaleId>ST06</SaleId>
						<SaleRefNb>S78-T06-0029</SaleRefNb>
						<SaleRcncltnId>S78-8469</SaleRcncltnId>
					</SaleCntxt>
				</Cntxt>
				<Tx>
					<TxId>
						<TxDtTm>2013-10-13T08:29:15+02:00</TxDtTm>
						<TxRef>002949</TxRef>
					</TxId>
					<TxSucss>true</TxSucss>
					<RcncltnId>8469</RcncltnId>
					<TxDtls>
						<Ccy>EUR</Ccy>
						<TtlAmt>43.14</TtlAmt>
						<ICCRltdData>XyoCCXiCAlwAhAegAAAAAxAQlQUAAACAAJoDCAcxnAEAnwIDAAMUnwkCAISfEAcGAQoDoAAAnxoDQkVMnyYI9FzN7o+vMUCfJwGAnzMD4PjInzQDHgMAnzUBIp82AgO8nzcEyDa2H59ABcAAsHAAigIwMJEIJqudNvJ2XEM=</ICCRltdData>
					</TxDtls>
					<AuthstnRslt>
						<AuthstnNtty>
							<Tp>CISS</Tp>
						</AuthstnNtty>
						<RspnToAuthstn>
							<Rspn>APPR</Rspn>
						</RspnToAuthstn>
						<AuthstnCd>032983</AuthstnCd>
					</AuthstnRslt>
				</Tx>
			 </Cmpltn>
			</Tx>
			<Tx>
			 <Cmpltn>
				<TxSeqCntr>2</TxSeqCntr>
				<Envt>
					<Card>
						<PrtctdCardData>
							<CnttTp>EVLP</CnttTp>
							<EnvlpdData>
								<Vrsn>0</Vrsn>
								<Rcpt>
									<KEK>
										<Vrsn>4</Vrsn>
										<KEKId>
											<KeyId>SpecV1TestDATKey</KeyId>
											<KeyVrsn>2010060715</KeyVrsn>
											<DerivtnId>OYclpQE=</DerivtnId>
										</KEKId>
										<KeyNcrptnAlgo>
											<Algo>DKP9</Algo>
										</KeyNcrptnAlgo>
										<NcrptdKey>4pAgABg=</NcrptdKey>
									</KEK>
								</Rcpt>
								<NcrptdCntt>
									<CnttTp>DATA</CnttTp>
									<CnttNcrptnAlgo>
										<Algo>E3DC</Algo>
										<Param>
											<InitlstnVctr>onu0bRwwbgk=</InitlstnVctr>
										</Param>
									</CnttNcrptnAlgo>
									<NcrptdData>WQ5D5YmLGunrJyRwZvvDSUqxb8Wq5O/q8wt/A5DYaD00VKZo+R3g0WNJ4CDSBgZrfSQT6CVYehVeb7w0lKsW/A==</NcrptdData>
								</NcrptdCntt>
							</EnvlpdData>
						</PrtctdCardData>
						<CardPdctPrfl>0001</CardPdctPrfl>
					</Card>
					<Crdhldr>
						<Authntcn>
							<AuthntcnMtd>FPIN</AuthntcnMtd>
							<AuthntcnNtty>ICCD</AuthntcnNtty>
						</Authntcn>
					</Crdhldr>
				</Envt>
				<Cntxt>
					<PmtCntxt>
						<CardPres>true</CardPres>
						<CrdhldrPres>true</CrdhldrPres>
						<OnLineCntxt>true</OnLineCntxt>
						<AttndncCntxt>ATTD</AttndncCntxt>
						<AttndntMsgCpbl>true</AttndntMsgCpbl>
						<CardDataNtryMd>CICC</CardDataNtryMd>
					</PmtCntxt>
					<SaleCntxt>
						<SaleId>ST05</SaleId>
						<SaleRefNb>S78-T05-0043</SaleRefNb>
						<SaleRcncltnId>S78-8469</SaleRcncltnId>
					</SaleCntxt>
				</Cntxt>
				<Tx>
					<TxId>
						<TxDtTm>2013-10-13T10:37:15+02:00</TxDtTm>
						<TxRef>002951</TxRef>
					</TxId>
					<TxSucss>true</TxSucss>
					<RcncltnId>8469</RcncltnId>
					<TxDtls>
						<Ccy>EUR</Ccy>
						<TtlAmt>25</TtlAmt>
						<ICCRltdData>XyoCCXiCAlwAhAegAAAAAxAQlQUAAACAAJoDCAcxnAEAnwIDAAMUnwkCAISfEAcGAQoDoAAAnxoDQkVMnyYI9FzN7o+vMUCfJwGAnzMD4PjInzQDHgMAnzUBIp82AgO8nzcEyDa2H59ABcAAsHAAigIwMJEIJqudNvJ2XEM=</ICCRltdData>
					</TxDtls>
					<AuthstnRslt>
						<AuthstnNtty>
							<Tp>CISS</Tp>
						</AuthstnNtty>
						<RspnToAuthstn>
							<Rspn>APPR</Rspn>
						</RspnToAuthstn>
						<AuthstnCd>987635</AuthstnCd>
					</AuthstnRslt>
				</Tx>
			 </Cmpltn>
			</Tx>
		 </DataSet>
		</BtchTrf>
	<SctyTrlr>
		<CnttTp>AUTH</CnttTp>
		<AuthntcdData>
			<Rcpt>
				<KEK>
					<KEKId>
						<KeyId>SpecV1TestKey</KeyId>
						<KeyVrsn>2010060715</KeyVrsn>
						<DerivtnId>OYclpQE=</DerivtnId>
					</KEKId>
					<KeyNcrptnAlgo>
						<Algo>DKP9</Algo>
					</KeyNcrptnAlgo>
					<NcrptdKey>4pAgABg=</NcrptdKey>
				</KEK>
			</Rcpt>
			<MACAlgo>
				<Algo>MCCS</Algo>
			</MACAlgo>
			<NcpsltdCntt>
				<CnttTp>DATA</CnttTp>
			</NcpsltdCntt>
			<MAC>JYmkLRCZWa0=</MAC>
		</AuthntcdData>
	</SctyTrlr>
	</AccptrBtchTrf>
</Document>